[
null,
{"id":1,"list":[{"code":101,"indent":0,"parameters":["",0,0,2]},{"code":401,"indent":0,"parameters":["~~~~~~~~~~"]},{"code":353,"indent":0,"parameters":[]},{"code":0,"indent":0,"parameters":[]}],"name":"人物死亡","switchId":11,"trigger":0},
{"id":2,"list":[{"code":111,"indent":0,"parameters":[1,5,0,1,0]},{"code":111,"indent":1,"parameters":[0,2,1]},{"code":250,"indent":2,"parameters":[{"name":"hwnwDam","volume":90,"pitch":100,"pan":0}]},{"code":0,"indent":2,"parameters":[]},{"code":412,"indent":1,"parameters":[]},{"code":0,"indent":1,"parameters":[]},{"code":412,"indent":0,"parameters":[]},{"code":111,"indent":0,"parameters":[1,5,0,2,0]},{"code":111,"indent":1,"parameters":[0,3,1]},{"code":250,"indent":2,"parameters":[{"name":"sywDam","volume":90,"pitch":100,"pan":0}]},{"code":0,"indent":2,"parameters":[]},{"code":412,"indent":1,"parameters":[]},{"code":0,"indent":1,"parameters":[]},{"code":412,"indent":0,"parameters":[]},{"code":111,"indent":0,"parameters":[1,5,0,3,0]},{"code":111,"indent":1,"parameters":[0,4,1]},{"code":250,"indent":2,"parameters":[{"name":"lslwDam","volume":90,"pitch":100,"pan":0}]},{"code":0,"indent":2,"parameters":[]},{"code":412,"indent":1,"parameters":[]},{"code":0,"indent":1,"parameters":[]},{"code":412,"indent":0,"parameters":[]},{"code":111,"indent":0,"parameters":[1,5,0,4,0]},{"code":111,"indent":1,"parameters":[0,5,1]},{"code":250,"indent":2,"parameters":[{"name":"mgwDam","volume":90,"pitch":100,"pan":0}]},{"code":0,"indent":2,"parameters":[]},{"code":412,"indent":1,"parameters":[]},{"code":0,"indent":1,"parameters":[]},{"code":412,"indent":0,"parameters":[]},{"code":111,"indent":0,"parameters":[1,5,0,5,0]},{"code":111,"indent":1,"parameters":[0,6,1]},{"code":250,"indent":2,"parameters":[{"name":"gtstrDam","volume":50,"pitch":100,"pan":0}]},{"code":0,"indent":2,"parameters":[]},{"code":412,"indent":1,"parameters":[]},{"code":0,"indent":1,"parameters":[]},{"code":412,"indent":0,"parameters":[]},{"code":0,"indent":0,"parameters":[]}],"name":"BOSS被攻击","switchId":1,"trigger":0},
{"id":3,"list":[{"code":0,"indent":0,"parameters":[]}],"name":"画面2.5","switchId":10,"trigger":0},
{"id":4,"list":[{"code":111,"indent":0,"parameters":[1,4,0,0,0]},{"code":356,"indent":1,"parameters":["ShowTalk"]},{"code":230,"indent":1,"parameters":[10]},{"code":122,"indent":1,"parameters":[4,4,0,0,1]},{"code":0,"indent":1,"parameters":[]},{"code":411,"indent":0,"parameters":[]},{"code":356,"indent":1,"parameters":["HideTalk"]},{"code":230,"indent":1,"parameters":[10]},{"code":122,"indent":1,"parameters":[4,4,0,0,0]},{"code":0,"indent":1,"parameters":[]},{"code":412,"indent":0,"parameters":[]},{"code":0,"indent":0,"parameters":[]}],"name":"显示聊天框","switchId":1,"trigger":0},
{"id":5,"list":[{"code":0,"indent":0,"parameters":[]}],"name":"","switchId":1,"trigger":0},
{"id":6,"list":[{"code":0,"indent":0,"parameters":[]}],"name":"","switchId":1,"trigger":0},
{"id":7,"list":[{"code":0,"indent":0,"parameters":[]}],"name":"","switchId":1,"trigger":0},
{"id":8,"list":[{"code":0,"indent":0,"parameters":[]}],"name":"","switchId":1,"trigger":0},
{"id":9,"list":[{"code":0,"indent":0,"parameters":[]}],"name":"","switchId":1,"trigger":0},
{"id":10,"list":[{"code":0,"indent":0,"parameters":[]}],"name":"","switchId":1,"trigger":0},
{"id":11,"list":[{"code":101,"indent":0,"parameters":["",0,0,1]},{"code":401,"indent":0,"parameters":["1111222222222222222222222222222222222222222222222"]},{"code":0,"indent":0,"parameters":[]}],"name":"","switchId":1,"trigger":0},
{"id":12,"list":[{"code":0,"indent":0,"parameters":[]}],"name":"","switchId":1,"trigger":0},
{"id":13,"list":[{"code":0,"indent":0,"parameters":[]}],"name":"","switchId":1,"trigger":0},
{"id":14,"list":[{"code":0,"indent":0,"parameters":[]}],"name":"","switchId":1,"trigger":0},
{"id":15,"list":[{"code":0,"indent":0,"parameters":[]}],"name":"","switchId":1,"trigger":0},
{"id":16,"list":[{"code":0,"indent":0,"parameters":[]}],"name":"","switchId":1,"trigger":0},
{"id":17,"list":[{"code":0,"indent":0,"parameters":[]}],"name":"","switchId":1,"trigger":0},
{"id":18,"list":[{"code":0,"indent":0,"parameters":[]}],"name":"","switchId":1,"trigger":0},
{"id":19,"list":[{"code":0,"indent":0,"parameters":[]}],"name":"","switchId":1,"trigger":0},
{"id":20,"list":[{"code":0,"indent":0,"parameters":[]}],"name":"","switchId":1,"trigger":0},
{"id":21,"list":[{"code":0,"indent":0,"parameters":[]}],"name":"","switchId":1,"trigger":0},
{"id":22,"list":[{"code":0,"indent":0,"parameters":[]}],"name":"","switchId":1,"trigger":0},
{"id":23,"list":[{"code":0,"indent":0,"parameters":[]}],"name":"","switchId":1,"trigger":0},
{"id":24,"list":[{"code":0,"indent":0,"parameters":[]}],"name":"","switchId":1,"trigger":0},
{"id":25,"list":[{"code":0,"indent":0,"parameters":[]}],"name":"","switchId":1,"trigger":0},
{"id":26,"list":[{"code":0,"indent":0,"parameters":[]}],"name":"","switchId":1,"trigger":0},
{"id":27,"list":[{"code":0,"indent":0,"parameters":[]}],"name":"","switchId":1,"trigger":0},
{"id":28,"list":[{"code":0,"indent":0,"parameters":[]}],"name":"","switchId":1,"trigger":0},
{"id":29,"list":[{"code":0,"indent":0,"parameters":[]}],"name":"","switchId":1,"trigger":0},
{"id":30,"list":[{"code":0,"indent":0,"parameters":[]}],"name":"","switchId":1,"trigger":0},
{"id":31,"list":[{"code":0,"indent":0,"parameters":[]}],"name":"","switchId":1,"trigger":0},
{"id":32,"list":[{"code":0,"indent":0,"parameters":[]}],"name":"","switchId":1,"trigger":0},
{"id":33,"list":[{"code":0,"indent":0,"parameters":[]}],"name":"","switchId":1,"trigger":0},
{"id":34,"list":[{"code":0,"indent":0,"parameters":[]}],"name":"","switchId":1,"trigger":0},
{"id":35,"list":[{"code":0,"indent":0,"parameters":[]}],"name":"","switchId":1,"trigger":0},
{"id":36,"list":[{"code":0,"indent":0,"parameters":[]}],"name":"","switchId":1,"trigger":0},
{"id":37,"list":[{"code":0,"indent":0,"parameters":[]}],"name":"","switchId":1,"trigger":0},
{"id":38,"list":[{"code":0,"indent":0,"parameters":[]}],"name":"","switchId":1,"trigger":0},
{"id":39,"list":[{"code":0,"indent":0,"parameters":[]}],"name":"","switchId":1,"trigger":0},
{"id":40,"list":[{"code":0,"indent":0,"parameters":[]}],"name":"","switchId":1,"trigger":0},
{"id":41,"list":[{"code":0,"indent":0,"parameters":[]}],"name":"","switchId":1,"trigger":0},
{"id":42,"list":[{"code":0,"indent":0,"parameters":[]}],"name":"","switchId":1,"trigger":0},
{"id":43,"list":[{"code":0,"indent":0,"parameters":[]}],"name":"","switchId":1,"trigger":0},
{"id":44,"list":[{"code":0,"indent":0,"parameters":[]}],"name":"","switchId":1,"trigger":0},
{"id":45,"list":[{"code":0,"indent":0,"parameters":[]}],"name":"","switchId":1,"trigger":0},
{"id":46,"list":[{"code":0,"indent":0,"parameters":[]}],"name":"","switchId":1,"trigger":0},
{"id":47,"list":[{"code":0,"indent":0,"parameters":[]}],"name":"","switchId":1,"trigger":0},
{"id":48,"list":[{"code":0,"indent":0,"parameters":[]}],"name":"","switchId":1,"trigger":0},
{"id":49,"list":[{"code":0,"indent":0,"parameters":[]}],"name":"","switchId":1,"trigger":0},
{"id":50,"list":[{"code":0,"indent":0,"parameters":[]}],"name":"","switchId":1,"trigger":0},
{"id":51,"list":[{"code":0,"indent":0,"parameters":[]}],"name":"","switchId":1,"trigger":0},
{"id":52,"list":[{"code":0,"indent":0,"parameters":[]}],"name":"","switchId":1,"trigger":0},
{"id":53,"list":[{"code":0,"indent":0,"parameters":[]}],"name":"","switchId":1,"trigger":0},
{"id":54,"list":[{"code":0,"indent":0,"parameters":[]}],"name":"","switchId":1,"trigger":0},
{"id":55,"list":[{"code":0,"indent":0,"parameters":[]}],"name":"","switchId":1,"trigger":0},
{"id":56,"list":[{"code":0,"indent":0,"parameters":[]}],"name":"","switchId":1,"trigger":0},
{"id":57,"list":[{"code":0,"indent":0,"parameters":[]}],"name":"","switchId":1,"trigger":0},
{"id":58,"list":[{"code":0,"indent":0,"parameters":[]}],"name":"","switchId":1,"trigger":0},
{"id":59,"list":[{"code":0,"indent":0,"parameters":[]}],"name":"","switchId":1,"trigger":0},
{"id":60,"list":[{"code":0,"indent":0,"parameters":[]}],"name":"","switchId":1,"trigger":0},
{"id":61,"list":[{"code":0,"indent":0,"parameters":[]}],"name":"","switchId":1,"trigger":0},
{"id":62,"list":[{"code":0,"indent":0,"parameters":[]}],"name":"","switchId":1,"trigger":0},
{"id":63,"list":[{"code":0,"indent":0,"parameters":[]}],"name":"","switchId":1,"trigger":0},
{"id":64,"list":[{"code":0,"indent":0,"parameters":[]}],"name":"","switchId":1,"trigger":0},
{"id":65,"list":[{"code":0,"indent":0,"parameters":[]}],"name":"","switchId":1,"trigger":0},
{"id":66,"list":[{"code":0,"indent":0,"parameters":[]}],"name":"","switchId":1,"trigger":0},
{"id":67,"list":[{"code":0,"indent":0,"parameters":[]}],"name":"","switchId":1,"trigger":0},
{"id":68,"list":[{"code":0,"indent":0,"parameters":[]}],"name":"","switchId":1,"trigger":0},
{"id":69,"list":[{"code":0,"indent":0,"parameters":[]}],"name":"","switchId":1,"trigger":0},
{"id":70,"list":[{"code":0,"indent":0,"parameters":[]}],"name":"","switchId":1,"trigger":0},
{"id":71,"list":[{"code":0,"indent":0,"parameters":[]}],"name":"","switchId":1,"trigger":0},
{"id":72,"list":[{"code":0,"indent":0,"parameters":[]}],"name":"","switchId":1,"trigger":0},
{"id":73,"list":[{"code":0,"indent":0,"parameters":[]}],"name":"","switchId":1,"trigger":0},
{"id":74,"list":[{"code":0,"indent":0,"parameters":[]}],"name":"","switchId":1,"trigger":0},
{"id":75,"list":[{"code":0,"indent":0,"parameters":[]}],"name":"","switchId":1,"trigger":0},
{"id":76,"list":[{"code":0,"indent":0,"parameters":[]}],"name":"","switchId":1,"trigger":0},
{"id":77,"list":[{"code":0,"indent":0,"parameters":[]}],"name":"","switchId":1,"trigger":0},
{"id":78,"list":[{"code":0,"indent":0,"parameters":[]}],"name":"","switchId":1,"trigger":0},
{"id":79,"list":[{"code":0,"indent":0,"parameters":[]}],"name":"","switchId":1,"trigger":0},
{"id":80,"list":[{"code":0,"indent":0,"parameters":[]}],"name":"","switchId":1,"trigger":0},
{"id":81,"list":[{"code":0,"indent":0,"parameters":[]}],"name":"","switchId":1,"trigger":0},
{"id":82,"list":[{"code":0,"indent":0,"parameters":[]}],"name":"","switchId":1,"trigger":0},
{"id":83,"list":[{"code":0,"indent":0,"parameters":[]}],"name":"","switchId":1,"trigger":0},
{"id":84,"list":[{"code":0,"indent":0,"parameters":[]}],"name":"","switchId":1,"trigger":0},
{"id":85,"list":[{"code":0,"indent":0,"parameters":[]}],"name":"","switchId":1,"trigger":0},
{"id":86,"list":[{"code":0,"indent":0,"parameters":[]}],"name":"","switchId":1,"trigger":0},
{"id":87,"list":[{"code":0,"indent":0,"parameters":[]}],"name":"","switchId":1,"trigger":0},
{"id":88,"list":[{"code":0,"indent":0,"parameters":[]}],"name":"","switchId":1,"trigger":0},
{"id":89,"list":[{"code":0,"indent":0,"parameters":[]}],"name":"","switchId":1,"trigger":0},
{"id":90,"list":[{"code":0,"indent":0,"parameters":[]}],"name":"","switchId":1,"trigger":0},
{"id":91,"list":[{"code":0,"indent":0,"parameters":[]}],"name":"","switchId":1,"trigger":0},
{"id":92,"list":[{"code":0,"indent":0,"parameters":[]}],"name":"","switchId":1,"trigger":0},
{"id":93,"list":[{"code":0,"indent":0,"parameters":[]}],"name":"","switchId":1,"trigger":0},
{"id":94,"list":[{"code":0,"indent":0,"parameters":[]}],"name":"","switchId":1,"trigger":0},
{"id":95,"list":[{"code":0,"indent":0,"parameters":[]}],"name":"","switchId":1,"trigger":0},
{"id":96,"list":[{"code":0,"indent":0,"parameters":[]}],"name":"","switchId":1,"trigger":0},
{"id":97,"list":[{"code":0,"indent":0,"parameters":[]}],"name":"","switchId":1,"trigger":0},
{"id":98,"list":[{"code":0,"indent":0,"parameters":[]}],"name":"","switchId":1,"trigger":0},
{"id":99,"list":[{"code":0,"indent":0,"parameters":[]}],"name":"","switchId":1,"trigger":0},
{"id":100,"list":[{"code":0,"indent":0,"parameters":[]}],"name":"","switchId":1,"trigger":0},
{"id":101,"list":[{"code":0,"indent":0,"parameters":[]}],"name":"","switchId":1,"trigger":0},
{"id":102,"list":[{"code":0,"indent":0,"parameters":[]}],"name":"","switchId":1,"trigger":0},
{"id":103,"list":[{"code":0,"indent":0,"parameters":[]}],"name":"","switchId":1,"trigger":0},
{"id":104,"list":[{"code":0,"indent":0,"parameters":[]}],"name":"","switchId":1,"trigger":0},
{"id":105,"list":[{"code":0,"indent":0,"parameters":[]}],"name":"","switchId":1,"trigger":0},
{"id":106,"list":[{"code":0,"indent":0,"parameters":[]}],"name":"","switchId":1,"trigger":0},
{"id":107,"list":[{"code":0,"indent":0,"parameters":[]}],"name":"","switchId":1,"trigger":0},
{"id":108,"list":[{"code":0,"indent":0,"parameters":[]}],"name":"","switchId":1,"trigger":0},
{"id":109,"list":[{"code":0,"indent":0,"parameters":[]}],"name":"","switchId":1,"trigger":0},
{"id":110,"list":[{"code":0,"indent":0,"parameters":[]}],"name":"","switchId":1,"trigger":0},
{"id":111,"list":[{"code":0,"indent":0,"parameters":[]}],"name":"","switchId":1,"trigger":0},
{"id":112,"list":[{"code":0,"indent":0,"parameters":[]}],"name":"","switchId":1,"trigger":0},
{"id":113,"list":[{"code":0,"indent":0,"parameters":[]}],"name":"","switchId":1,"trigger":0},
{"id":114,"list":[{"code":0,"indent":0,"parameters":[]}],"name":"","switchId":1,"trigger":0},
{"id":115,"list":[{"code":0,"indent":0,"parameters":[]}],"name":"","switchId":1,"trigger":0},
{"id":116,"list":[{"code":0,"indent":0,"parameters":[]}],"name":"","switchId":1,"trigger":0},
{"id":117,"list":[{"code":0,"indent":0,"parameters":[]}],"name":"","switchId":1,"trigger":0},
{"id":118,"list":[{"code":0,"indent":0,"parameters":[]}],"name":"","switchId":1,"trigger":0},
{"id":119,"list":[{"code":0,"indent":0,"parameters":[]}],"name":"","switchId":1,"trigger":0},
{"id":120,"list":[{"code":0,"indent":0,"parameters":[]}],"name":"","switchId":1,"trigger":0},
{"id":121,"list":[{"code":0,"indent":0,"parameters":[]}],"name":"","switchId":1,"trigger":0},
{"id":122,"list":[{"code":0,"indent":0,"parameters":[]}],"name":"","switchId":1,"trigger":0},
{"id":123,"list":[{"code":0,"indent":0,"parameters":[]}],"name":"","switchId":1,"trigger":0},
{"id":124,"list":[{"code":0,"indent":0,"parameters":[]}],"name":"","switchId":1,"trigger":0},
{"id":125,"list":[{"code":0,"indent":0,"parameters":[]}],"name":"","switchId":1,"trigger":0},
{"id":126,"list":[{"code":0,"indent":0,"parameters":[]}],"name":"","switchId":1,"trigger":0},
{"id":127,"list":[{"code":0,"indent":0,"parameters":[]}],"name":"","switchId":1,"trigger":0},
{"id":128,"list":[{"code":0,"indent":0,"parameters":[]}],"name":"","switchId":1,"trigger":0},
{"id":129,"list":[{"code":0,"indent":0,"parameters":[]}],"name":"","switchId":1,"trigger":0},
{"id":130,"list":[{"code":0,"indent":0,"parameters":[]}],"name":"","switchId":1,"trigger":0},
{"id":131,"list":[{"code":0,"indent":0,"parameters":[]}],"name":"","switchId":1,"trigger":0},
{"id":132,"list":[{"code":0,"indent":0,"parameters":[]}],"name":"","switchId":1,"trigger":0},
{"id":133,"list":[{"code":0,"indent":0,"parameters":[]}],"name":"","switchId":1,"trigger":0},
{"id":134,"list":[{"code":0,"indent":0,"parameters":[]}],"name":"","switchId":1,"trigger":0},
{"id":135,"list":[{"code":0,"indent":0,"parameters":[]}],"name":"","switchId":1,"trigger":0},
{"id":136,"list":[{"code":0,"indent":0,"parameters":[]}],"name":"","switchId":1,"trigger":0},
{"id":137,"list":[{"code":0,"indent":0,"parameters":[]}],"name":"","switchId":1,"trigger":0},
{"id":138,"list":[{"code":0,"indent":0,"parameters":[]}],"name":"","switchId":1,"trigger":0},
{"id":139,"list":[{"code":0,"indent":0,"parameters":[]}],"name":"","switchId":1,"trigger":0},
{"id":140,"list":[{"code":0,"indent":0,"parameters":[]}],"name":"","switchId":1,"trigger":0},
{"id":141,"list":[{"code":0,"indent":0,"parameters":[]}],"name":"","switchId":1,"trigger":0},
{"id":142,"list":[{"code":0,"indent":0,"parameters":[]}],"name":"","switchId":1,"trigger":0},
{"id":143,"list":[{"code":0,"indent":0,"parameters":[]}],"name":"","switchId":1,"trigger":0},
{"id":144,"list":[{"code":0,"indent":0,"parameters":[]}],"name":"","switchId":1,"trigger":0},
{"id":145,"list":[{"code":0,"indent":0,"parameters":[]}],"name":"","switchId":1,"trigger":0},
{"id":146,"list":[{"code":0,"indent":0,"parameters":[]}],"name":"","switchId":1,"trigger":0},
{"id":147,"list":[{"code":0,"indent":0,"parameters":[]}],"name":"","switchId":1,"trigger":0},
{"id":148,"list":[{"code":0,"indent":0,"parameters":[]}],"name":"","switchId":1,"trigger":0},
{"id":149,"list":[{"code":0,"indent":0,"parameters":[]}],"name":"","switchId":1,"trigger":0},
{"id":150,"list":[{"code":0,"indent":0,"parameters":[]}],"name":"","switchId":1,"trigger":0},
{"id":151,"list":[{"code":0,"indent":0,"parameters":[]}],"name":"","switchId":1,"trigger":0},
{"id":152,"list":[{"code":0,"indent":0,"parameters":[]}],"name":"","switchId":1,"trigger":0},
{"id":153,"list":[{"code":0,"indent":0,"parameters":[]}],"name":"","switchId":1,"trigger":0},
{"id":154,"list":[{"code":0,"indent":0,"parameters":[]}],"name":"","switchId":1,"trigger":0},
{"id":155,"list":[{"code":0,"indent":0,"parameters":[]}],"name":"","switchId":1,"trigger":0},
{"id":156,"list":[{"code":0,"indent":0,"parameters":[]}],"name":"","switchId":1,"trigger":0},
{"id":157,"list":[{"code":0,"indent":0,"parameters":[]}],"name":"","switchId":1,"trigger":0},
{"id":158,"list":[{"code":0,"indent":0,"parameters":[]}],"name":"","switchId":1,"trigger":0},
{"id":159,"list":[{"code":0,"indent":0,"parameters":[]}],"name":"","switchId":1,"trigger":0},
{"id":160,"list":[{"code":0,"indent":0,"parameters":[]}],"name":"","switchId":1,"trigger":0},
{"id":161,"list":[{"code":0,"indent":0,"parameters":[]}],"name":"","switchId":1,"trigger":0},
{"id":162,"list":[{"code":0,"indent":0,"parameters":[]}],"name":"","switchId":1,"trigger":0},
{"id":163,"list":[{"code":0,"indent":0,"parameters":[]}],"name":"","switchId":1,"trigger":0},
{"id":164,"list":[{"code":0,"indent":0,"parameters":[]}],"name":"","switchId":1,"trigger":0},
{"id":165,"list":[{"code":0,"indent":0,"parameters":[]}],"name":"","switchId":1,"trigger":0},
{"id":166,"list":[{"code":0,"indent":0,"parameters":[]}],"name":"","switchId":1,"trigger":0},
{"id":167,"list":[{"code":0,"indent":0,"parameters":[]}],"name":"","switchId":1,"trigger":0},
{"id":168,"list":[{"code":0,"indent":0,"parameters":[]}],"name":"","switchId":1,"trigger":0},
{"id":169,"list":[{"code":0,"indent":0,"parameters":[]}],"name":"","switchId":1,"trigger":0},
{"id":170,"list":[{"code":0,"indent":0,"parameters":[]}],"name":"","switchId":1,"trigger":0},
{"id":171,"list":[{"code":0,"indent":0,"parameters":[]}],"name":"","switchId":1,"trigger":0},
{"id":172,"list":[{"code":0,"indent":0,"parameters":[]}],"name":"","switchId":1,"trigger":0},
{"id":173,"list":[{"code":0,"indent":0,"parameters":[]}],"name":"","switchId":1,"trigger":0},
{"id":174,"list":[{"code":0,"indent":0,"parameters":[]}],"name":"","switchId":1,"trigger":0},
{"id":175,"list":[{"code":0,"indent":0,"parameters":[]}],"name":"","switchId":1,"trigger":0},
{"id":176,"list":[{"code":0,"indent":0,"parameters":[]}],"name":"","switchId":1,"trigger":0},
{"id":177,"list":[{"code":0,"indent":0,"parameters":[]}],"name":"","switchId":1,"trigger":0},
{"id":178,"list":[{"code":0,"indent":0,"parameters":[]}],"name":"","switchId":1,"trigger":0},
{"id":179,"list":[{"code":0,"indent":0,"parameters":[]}],"name":"","switchId":1,"trigger":0},
{"id":180,"list":[{"code":0,"indent":0,"parameters":[]}],"name":"","switchId":1,"trigger":0},
{"id":181,"list":[{"code":0,"indent":0,"parameters":[]}],"name":"","switchId":1,"trigger":0},
{"id":182,"list":[{"code":0,"indent":0,"parameters":[]}],"name":"","switchId":1,"trigger":0},
{"id":183,"list":[{"code":0,"indent":0,"parameters":[]}],"name":"","switchId":1,"trigger":0},
{"id":184,"list":[{"code":0,"indent":0,"parameters":[]}],"name":"","switchId":1,"trigger":0},
{"id":185,"list":[{"code":0,"indent":0,"parameters":[]}],"name":"","switchId":1,"trigger":0},
{"id":186,"list":[{"code":0,"indent":0,"parameters":[]}],"name":"","switchId":1,"trigger":0},
{"id":187,"list":[{"code":0,"indent":0,"parameters":[]}],"name":"","switchId":1,"trigger":0},
{"id":188,"list":[{"code":0,"indent":0,"parameters":[]}],"name":"","switchId":1,"trigger":0},
{"id":189,"list":[{"code":0,"indent":0,"parameters":[]}],"name":"","switchId":1,"trigger":0},
{"id":190,"list":[{"code":0,"indent":0,"parameters":[]}],"name":"","switchId":1,"trigger":0},
{"id":191,"list":[{"code":0,"indent":0,"parameters":[]}],"name":"","switchId":1,"trigger":0},
{"id":192,"list":[{"code":0,"indent":0,"parameters":[]}],"name":"","switchId":1,"trigger":0},
{"id":193,"list":[{"code":0,"indent":0,"parameters":[]}],"name":"","switchId":1,"trigger":0},
{"id":194,"list":[{"code":0,"indent":0,"parameters":[]}],"name":"","switchId":1,"trigger":0},
{"id":195,"list":[{"code":0,"indent":0,"parameters":[]}],"name":"","switchId":1,"trigger":0},
{"id":196,"list":[{"code":0,"indent":0,"parameters":[]}],"name":"","switchId":1,"trigger":0},
{"id":197,"list":[{"code":0,"indent":0,"parameters":[]}],"name":"","switchId":1,"trigger":0},
{"id":198,"list":[{"code":102,"indent":0,"parameters":[["显示HP/MP界面","隐藏HP/MP界面"],1,0,1,0]},{"code":402,"indent":0,"parameters":[0,"显示HP/MP界面"]},{"code":356,"indent":1,"parameters":["show_actor_hud"]},{"code":356,"indent":1,"parameters":["ct_hud_visible : true"]},{"code":231,"indent":1,"parameters":[100,"Layout",0,0,0,0,100,100,255,0]},{"code":231,"indent":1,"parameters":[99,"EXP",0,0,0,759,100,100,255,0]},{"code":0,"indent":1,"parameters":[]},{"code":402,"indent":0,"parameters":[1,"隐藏HP/MP界面"]},{"code":356,"indent":1,"parameters":["hide_actor_hud"]},{"code":356,"indent":1,"parameters":["ct_hud_visible : false"]},{"code":235,"indent":1,"parameters":[100]},{"code":235,"indent":1,"parameters":[99]},{"code":0,"indent":1,"parameters":[]},{"code":404,"indent":0,"parameters":[]},{"code":0,"indent":0,"parameters":[]}],"name":"隐藏HPMP界面","switchId":1,"trigger":0},
{"id":199,"list":[{"code":102,"indent":0,"parameters":[["显示技能UI界面","隐藏技能UI界面"],1,0,1,0]},{"code":402,"indent":0,"parameters":[0,"显示技能UI界面"]},{"code":355,"indent":1,"parameters":["$gameSystem._hideBtns = false;"]},{"code":231,"indent":1,"parameters":[98,"UI",0,0,450,685,100,100,255,0]},{"code":0,"indent":1,"parameters":[]},{"code":402,"indent":0,"parameters":[1,"隐藏技能UI界面"]},{"code":355,"indent":1,"parameters":["$gameSystem._hideBtns = true;"]},{"code":235,"indent":1,"parameters":[98]},{"code":0,"indent":1,"parameters":[]},{"code":404,"indent":0,"parameters":[]},{"code":0,"indent":0,"parameters":[]}],"name":"隐藏UI界面","switchId":1,"trigger":0},
{"id":200,"list":[{"code":121,"indent":0,"parameters":[23,23,0]},{"code":104,"indent":0,"parameters":[199,1]},{"code":0,"indent":0,"parameters":[]}],"name":"道具选择界面","switchId":1,"trigger":0},
{"id":201,"list":[{"code":111,"indent":0,"parameters":[1,199,0,1,0]},{"code":356,"indent":1,"parameters":["set_actor_item : 1 : 1"]},{"code":0,"indent":1,"parameters":[]},{"code":412,"indent":0,"parameters":[]},{"code":111,"indent":0,"parameters":[1,199,0,2,0]},{"code":356,"indent":1,"parameters":["set_actor_item : 1 : 2"]},{"code":0,"indent":1,"parameters":[]},{"code":412,"indent":0,"parameters":[]},{"code":111,"indent":0,"parameters":[1,199,0,3,0]},{"code":356,"indent":1,"parameters":["set_actor_item : 1 : 3"]},{"code":0,"indent":1,"parameters":[]},{"code":412,"indent":0,"parameters":[]},{"code":111,"indent":0,"parameters":[1,199,0,4,0]},{"code":356,"indent":1,"parameters":["set_actor_item : 1 : 4"]},{"code":0,"indent":1,"parameters":[]},{"code":412,"indent":0,"parameters":[]},{"code":111,"indent":0,"parameters":[1,199,0,5,0]},{"code":356,"indent":1,"parameters":["set_actor_item : 1 : 5"]},{"code":0,"indent":1,"parameters":[]},{"code":412,"indent":0,"parameters":[]},{"code":111,"indent":0,"parameters":[1,199,0,6,0]},{"code":356,"indent":1,"parameters":["set_actor_item : 1 : 6"]},{"code":0,"indent":1,"parameters":[]},{"code":412,"indent":0,"parameters":[]},{"code":111,"indent":0,"parameters":[1,199,0,7,0]},{"code":356,"indent":1,"parameters":["set_actor_item : 1 : 7"]},{"code":0,"indent":1,"parameters":[]},{"code":412,"indent":0,"parameters":[]},{"code":111,"indent":0,"parameters":[1,199,0,8,0]},{"code":356,"indent":1,"parameters":["set_actor_item : 1 : 8"]},{"code":0,"indent":1,"parameters":[]},{"code":412,"indent":0,"parameters":[]},{"code":111,"indent":0,"parameters":[1,199,0,9,0]},{"code":356,"indent":1,"parameters":["set_actor_item : 1 : 9"]},{"code":0,"indent":1,"parameters":[]},{"code":412,"indent":0,"parameters":[]},{"code":111,"indent":0,"parameters":[1,199,0,10,0]},{"code":356,"indent":1,"parameters":["set_actor_item : 1 : 10"]},{"code":0,"indent":1,"parameters":[]},{"code":412,"indent":0,"parameters":[]},{"code":111,"indent":0,"parameters":[1,199,0,11,0]},{"code":356,"indent":1,"parameters":["set_actor_item : 1 : 11"]},{"code":0,"indent":1,"parameters":[]},{"code":412,"indent":0,"parameters":[]},{"code":111,"indent":0,"parameters":[1,199,0,12,0]},{"code":356,"indent":1,"parameters":["set_actor_item : 1 : 12"]},{"code":0,"indent":1,"parameters":[]},{"code":412,"indent":0,"parameters":[]},{"code":111,"indent":0,"parameters":[1,199,0,13,0]},{"code":356,"indent":1,"parameters":["set_actor_item : 1 : 13"]},{"code":0,"indent":1,"parameters":[]},{"code":412,"indent":0,"parameters":[]},{"code":111,"indent":0,"parameters":[1,199,0,14,0]},{"code":356,"indent":1,"parameters":["set_actor_item : 1 : 14"]},{"code":0,"indent":1,"parameters":[]},{"code":412,"indent":0,"parameters":[]},{"code":0,"indent":0,"parameters":[]}],"name":"道具选择","switchId":23,"trigger":2},
{"id":202,"list":[{"code":121,"indent":0,"parameters":[203,203,0]},{"code":231,"indent":0,"parameters":[1,"bnzs",0,0,298,100,100,100,255,0]},{"code":355,"indent":0,"parameters":["this.pluginCommand(\"MapSelectSkill\",[\"204\",\"1\",\"1\"])"]},{"code":235,"indent":0,"parameters":[1]},{"code":0,"indent":0,"parameters":[]}],"name":"---------技能1选择界面","switchId":1,"trigger":0},
{"id":203,"list":[{"code":111,"indent":0,"parameters":[1,204,0,0,1]},{"code":355,"indent":1,"parameters":["Galv.SBTNS.addButton(1,'map',1 * 0 + $gameVariables.value(204) ,460,688,['event',202],255);"]},{"code":121,"indent":1,"parameters":[203,203,1]},{"code":0,"indent":1,"parameters":[]},{"code":412,"indent":0,"parameters":[]},{"code":0,"indent":0,"parameters":[]}],"name":"技能1更换","switchId":203,"trigger":1},
{"id":204,"list":[{"code":111,"indent":0,"parameters":[1,204,0,0,1]},{"code":205,"indent":1,"parameters":[-1,{"list":[{"code":45,"parameters":["this.act($gameVariables.value(204))"],"indent":null},{"code":0}],"repeat":false,"skippable":false,"wait":false}]},{"code":505,"indent":1,"parameters":[{"code":45,"parameters":["this.act($gameVariables.value(204))"],"indent":null}]},{"code":0,"indent":1,"parameters":[]},{"code":412,"indent":0,"parameters":[]},{"code":0,"indent":0,"parameters":[]}],"name":"技能1","switchId":26,"trigger":0},
{"id":205,"list":[{"code":121,"indent":0,"parameters":[206,206,0]},{"code":231,"indent":0,"parameters":[1,"bnzs",0,0,298,100,100,100,255,0]},{"code":355,"indent":0,"parameters":["this.pluginCommand(\"MapSelectSkill\",[\"207\",\"1\",\"1\"])"]},{"code":235,"indent":0,"parameters":[1]},{"code":0,"indent":0,"parameters":[]}],"name":"---------技能2选择界面","switchId":1,"trigger":0},
{"id":206,"list":[{"code":111,"indent":0,"parameters":[1,207,0,0,1]},{"code":355,"indent":1,"parameters":["Galv.SBTNS.addButton(2,'map',1 * 0 + $gameVariables.value(207) ,495,688,['event',205],255);"]},{"code":121,"indent":1,"parameters":[206,206,1]},{"code":0,"indent":1,"parameters":[]},{"code":412,"indent":0,"parameters":[]},{"code":0,"indent":0,"parameters":[]}],"name":"技能2更换","switchId":206,"trigger":1},
{"id":207,"list":[{"code":111,"indent":0,"parameters":[1,207,0,0,1]},{"code":205,"indent":1,"parameters":[-1,{"list":[{"code":45,"parameters":["this.act($gameVariables.value(207))"],"indent":null},{"code":0}],"repeat":false,"skippable":false,"wait":false}]},{"code":505,"indent":1,"parameters":[{"code":45,"parameters":["this.act($gameVariables.value(207))"],"indent":null}]},{"code":0,"indent":1,"parameters":[]},{"code":412,"indent":0,"parameters":[]},{"code":0,"indent":0,"parameters":[]}],"name":"技能2","switchId":26,"trigger":0},
{"id":208,"list":[{"code":121,"indent":0,"parameters":[209,209,0]},{"code":231,"indent":0,"parameters":[1,"bnzs",0,0,298,100,100,100,255,0]},{"code":355,"indent":0,"parameters":["this.pluginCommand(\"MapSelectSkill\",[\"210\",\"1\",\"1\"])"]},{"code":235,"indent":0,"parameters":[1]},{"code":0,"indent":0,"parameters":[]}],"name":"---------技能3选择界面","switchId":1,"trigger":0},
{"id":209,"list":[{"code":111,"indent":0,"parameters":[1,210,0,0,1]},{"code":355,"indent":1,"parameters":["Galv.SBTNS.addButton(3,'map',1 * 0 + $gameVariables.value(210) ,530,688,['event',208],255);"]},{"code":121,"indent":1,"parameters":[209,209,1]},{"code":0,"indent":1,"parameters":[]},{"code":412,"indent":0,"parameters":[]},{"code":0,"indent":0,"parameters":[]}],"name":"技能3更换","switchId":209,"trigger":1},
{"id":210,"list":[{"code":111,"indent":0,"parameters":[1,210,0,0,1]},{"code":205,"indent":1,"parameters":[-1,{"list":[{"code":45,"parameters":["this.act($gameVariables.value(210))"],"indent":null},{"code":0}],"repeat":false,"skippable":false,"wait":false}]},{"code":505,"indent":1,"parameters":[{"code":45,"parameters":["this.act($gameVariables.value(210))"],"indent":null}]},{"code":0,"indent":1,"parameters":[]},{"code":412,"indent":0,"parameters":[]},{"code":0,"indent":0,"parameters":[]}],"name":"技能3","switchId":26,"trigger":0},
{"id":211,"list":[{"code":121,"indent":0,"parameters":[212,212,0]},{"code":231,"indent":0,"parameters":[1,"bnzs",0,0,298,100,100,100,255,0]},{"code":355,"indent":0,"parameters":["this.pluginCommand(\"MapSelectSkill\",[\"213\",\"1\",\"1\"])"]},{"code":235,"indent":0,"parameters":[1]},{"code":0,"indent":0,"parameters":[]}],"name":"---------技能4选择界面","switchId":1,"trigger":0},
{"id":212,"list":[{"code":111,"indent":0,"parameters":[1,213,0,0,1]},{"code":355,"indent":1,"parameters":["Galv.SBTNS.addButton(4,'map',1 * 0 + $gameVariables.value(213) ,565,688,['event',211],255);"]},{"code":121,"indent":1,"parameters":[212,212,1]},{"code":0,"indent":1,"parameters":[]},{"code":412,"indent":0,"parameters":[]},{"code":0,"indent":0,"parameters":[]}],"name":"技能4更换","switchId":212,"trigger":1},
{"id":213,"list":[{"code":111,"indent":0,"parameters":[1,213,0,0,1]},{"code":205,"indent":1,"parameters":[-1,{"list":[{"code":45,"parameters":["this.act($gameVariables.value(213))"],"indent":null},{"code":0}],"repeat":false,"skippable":false,"wait":false}]},{"code":505,"indent":1,"parameters":[{"code":45,"parameters":["this.act($gameVariables.value(213))"],"indent":null}]},{"code":0,"indent":1,"parameters":[]},{"code":412,"indent":0,"parameters":[]},{"code":0,"indent":0,"parameters":[]}],"name":"技能4","switchId":26,"trigger":0},
{"id":214,"list":[{"code":121,"indent":0,"parameters":[215,215,0]},{"code":231,"indent":0,"parameters":[1,"bnzs",0,0,298,100,100,100,255,0]},{"code":355,"indent":0,"parameters":["this.pluginCommand(\"MapSelectSkill\",[\"216\",\"1\",\"1\"])"]},{"code":235,"indent":0,"parameters":[1]},{"code":0,"indent":0,"parameters":[]}],"name":"---------技能Q选择界面","switchId":1,"trigger":0},
{"id":215,"list":[{"code":111,"indent":0,"parameters":[1,216,0,0,1]},{"code":355,"indent":1,"parameters":["Galv.SBTNS.addButton(5,'map',1 * 0 + $gameVariables.value(216) ,460,723,['event',214],255);"]},{"code":121,"indent":1,"parameters":[215,215,1]},{"code":0,"indent":1,"parameters":[]},{"code":412,"indent":0,"parameters":[]},{"code":0,"indent":0,"parameters":[]}],"name":"技能Q更换","switchId":215,"trigger":1},
{"id":216,"list":[{"code":111,"indent":0,"parameters":[1,216,0,0,1]},{"code":205,"indent":1,"parameters":[-1,{"list":[{"code":45,"parameters":["this.act($gameVariables.value(216))"],"indent":null},{"code":0}],"repeat":false,"skippable":false,"wait":false}]},{"code":505,"indent":1,"parameters":[{"code":45,"parameters":["this.act($gameVariables.value(216))"],"indent":null}]},{"code":0,"indent":1,"parameters":[]},{"code":412,"indent":0,"parameters":[]},{"code":0,"indent":0,"parameters":[]}],"name":"技能Q","switchId":26,"trigger":0},
{"id":217,"list":[{"code":121,"indent":0,"parameters":[218,218,0]},{"code":231,"indent":0,"parameters":[1,"bnzs",0,0,298,100,100,100,255,0]},{"code":355,"indent":0,"parameters":["this.pluginCommand(\"MapSelectSkill\",[\"219\",\"1\",\"1\"])"]},{"code":235,"indent":0,"parameters":[1]},{"code":0,"indent":0,"parameters":[]}],"name":"---------技能W选择界面","switchId":1,"trigger":0},
{"id":218,"list":[{"code":111,"indent":0,"parameters":[1,219,0,0,1]},{"code":355,"indent":1,"parameters":["Galv.SBTNS.addButton(6,'map',1 * 0 + $gameVariables.value(219) ,495,723,['event',217],255);"]},{"code":121,"indent":1,"parameters":[218,218,1]},{"code":0,"indent":1,"parameters":[]},{"code":412,"indent":0,"parameters":[]},{"code":0,"indent":0,"parameters":[]}],"name":"技能W更换","switchId":218,"trigger":1},
{"id":219,"list":[{"code":111,"indent":0,"parameters":[1,219,0,0,1]},{"code":205,"indent":1,"parameters":[-1,{"list":[{"code":45,"parameters":["this.act($gameVariables.value(219))"],"indent":null},{"code":0}],"repeat":false,"skippable":false,"wait":false}]},{"code":505,"indent":1,"parameters":[{"code":45,"parameters":["this.act($gameVariables.value(219))"],"indent":null}]},{"code":0,"indent":1,"parameters":[]},{"code":412,"indent":0,"parameters":[]},{"code":0,"indent":0,"parameters":[]}],"name":"技能W","switchId":26,"trigger":0},
{"id":220,"list":[{"code":121,"indent":0,"parameters":[221,221,0]},{"code":231,"indent":0,"parameters":[1,"bnzs",0,0,298,100,100,100,255,0]},{"code":355,"indent":0,"parameters":["this.pluginCommand(\"MapSelectSkill\",[\"222\",\"1\",\"1\"])"]},{"code":235,"indent":0,"parameters":[1]},{"code":0,"indent":0,"parameters":[]}],"name":"---------技能E选择界面","switchId":1,"trigger":0},
{"id":221,"list":[{"code":111,"indent":0,"parameters":[1,190,0,0,1]},{"code":355,"indent":1,"parameters":["Galv.SBTNS.addButton(7,'map',1 * 0 + $gameVariables.value(222) ,530,723,['event',220],255);"]},{"code":121,"indent":1,"parameters":[221,221,1]},{"code":0,"indent":1,"parameters":[]},{"code":412,"indent":0,"parameters":[]},{"code":0,"indent":0,"parameters":[]}],"name":"技能E更换","switchId":221,"trigger":1},
{"id":222,"list":[{"code":111,"indent":0,"parameters":[1,222,0,0,1]},{"code":205,"indent":1,"parameters":[-1,{"list":[{"code":45,"parameters":["this.act($gameVariables.value(222))"],"indent":null},{"code":0}],"repeat":false,"skippable":false,"wait":false}]},{"code":505,"indent":1,"parameters":[{"code":45,"parameters":["this.act($gameVariables.value(222))"],"indent":null}]},{"code":0,"indent":1,"parameters":[]},{"code":412,"indent":0,"parameters":[]},{"code":0,"indent":0,"parameters":[]}],"name":"技能E","switchId":26,"trigger":0},
{"id":223,"list":[{"code":121,"indent":0,"parameters":[224,224,0]},{"code":231,"indent":0,"parameters":[1,"bnzs",0,0,298,100,100,100,255,0]},{"code":355,"indent":0,"parameters":["this.pluginCommand(\"MapSelectSkill\",[\"225\",\"1\",\"1\"])"]},{"code":235,"indent":0,"parameters":[1]},{"code":0,"indent":0,"parameters":[]}],"name":"---------技能R选择界面","switchId":1,"trigger":0},
{"id":224,"list":[{"code":111,"indent":0,"parameters":[1,225,0,0,1]},{"code":355,"indent":1,"parameters":["Galv.SBTNS.addButton(8,'map',1 * 0 + $gameVariables.value(225) ,565,723,['event',223],255);"]},{"code":121,"indent":1,"parameters":[224,224,1]},{"code":0,"indent":1,"parameters":[]},{"code":412,"indent":0,"parameters":[]},{"code":0,"indent":0,"parameters":[]}],"name":"技能R更换","switchId":224,"trigger":1},
{"id":225,"list":[{"code":111,"indent":0,"parameters":[1,225,0,0,1]},{"code":205,"indent":1,"parameters":[-1,{"list":[{"code":45,"parameters":["this.act($gameVariables.value(225))"],"indent":null},{"code":0}],"repeat":false,"skippable":false,"wait":false}]},{"code":505,"indent":1,"parameters":[{"code":45,"parameters":["this.act($gameVariables.value(225))"],"indent":null}]},{"code":0,"indent":1,"parameters":[]},{"code":412,"indent":0,"parameters":[]},{"code":0,"indent":0,"parameters":[]}],"name":"技能R","switchId":26,"trigger":0},
{"id":226,"list":[{"code":121,"indent":0,"parameters":[227,227,0]},{"code":231,"indent":0,"parameters":[1,"bnzs",0,0,298,100,100,100,255,0]},{"code":355,"indent":0,"parameters":["this.pluginCommand(\"MapSelectSkill\",[\"228\",\"1\",\"1\"])"]},{"code":235,"indent":0,"parameters":[1]},{"code":0,"indent":0,"parameters":[]}],"name":"---------技能A选择界面","switchId":1,"trigger":0},
{"id":227,"list":[{"code":111,"indent":0,"parameters":[1,228,0,0,1]},{"code":355,"indent":1,"parameters":["Galv.SBTNS.addButton(9,'map',1 * 0 + $gameVariables.value(228) ,600,688,['event',226],255);"]},{"code":121,"indent":1,"parameters":[227,227,1]},{"code":0,"indent":1,"parameters":[]},{"code":412,"indent":0,"parameters":[]},{"code":0,"indent":0,"parameters":[]}],"name":"技能A更换","switchId":227,"trigger":1},
{"id":228,"list":[{"code":111,"indent":0,"parameters":[1,228,0,0,1]},{"code":205,"indent":1,"parameters":[-1,{"list":[{"code":45,"parameters":["this.act($gameVariables.value(228))"],"indent":null},{"code":0}],"repeat":false,"skippable":false,"wait":false}]},{"code":505,"indent":1,"parameters":[{"code":45,"parameters":["this.act($gameVariables.value(228))"],"indent":null}]},{"code":0,"indent":1,"parameters":[]},{"code":412,"indent":0,"parameters":[]},{"code":0,"indent":0,"parameters":[]}],"name":"技能A","switchId":26,"trigger":0},
{"id":229,"list":[{"code":121,"indent":0,"parameters":[230,230,0]},{"code":231,"indent":0,"parameters":[1,"bnzs",0,0,298,100,100,100,255,0]},{"code":355,"indent":0,"parameters":["this.pluginCommand(\"MapSelectSkill\",[\"231\",\"1\",\"1\"])"]},{"code":235,"indent":0,"parameters":[1]},{"code":0,"indent":0,"parameters":[]}],"name":"---------技能S选择界面","switchId":1,"trigger":0},
{"id":230,"list":[{"code":111,"indent":0,"parameters":[1,231,0,0,1]},{"code":355,"indent":1,"parameters":["Galv.SBTNS.addButton(10,'map',1 * 0 + $gameVariables.value(231) ,635,688,['event',229],255);"]},{"code":121,"indent":1,"parameters":[230,230,1]},{"code":0,"indent":1,"parameters":[]},{"code":412,"indent":0,"parameters":[]},{"code":0,"indent":0,"parameters":[]}],"name":"技能S更换","switchId":230,"trigger":1},
{"id":231,"list":[{"code":111,"indent":0,"parameters":[1,231,0,0,1]},{"code":205,"indent":1,"parameters":[-1,{"list":[{"code":45,"parameters":["this.act($gameVariables.value(231))"],"indent":null},{"code":0}],"repeat":false,"skippable":false,"wait":false}]},{"code":505,"indent":1,"parameters":[{"code":45,"parameters":["this.act($gameVariables.value(231))"],"indent":null}]},{"code":0,"indent":1,"parameters":[]},{"code":412,"indent":0,"parameters":[]},{"code":0,"indent":0,"parameters":[]}],"name":"技能S","switchId":26,"trigger":0},
{"id":232,"list":[{"code":121,"indent":0,"parameters":[233,233,0]},{"code":231,"indent":0,"parameters":[1,"bnzs",0,0,298,100,100,100,255,0]},{"code":355,"indent":0,"parameters":["this.pluginCommand(\"MapSelectSkill\",[\"234\",\"1\",\"1\"])"]},{"code":235,"indent":0,"parameters":[1]},{"code":0,"indent":0,"parameters":[]}],"name":"---------技能D选择界面","switchId":1,"trigger":0},
{"id":233,"list":[{"code":111,"indent":0,"parameters":[1,234,0,0,1]},{"code":355,"indent":1,"parameters":["Galv.SBTNS.addButton(11,'map',1 * 0 + $gameVariables.value(234) ,670,688,['event',232],255);"]},{"code":121,"indent":1,"parameters":[233,233,1]},{"code":0,"indent":1,"parameters":[]},{"code":412,"indent":0,"parameters":[]},{"code":0,"indent":0,"parameters":[]}],"name":"技能D更换","switchId":233,"trigger":1},
{"id":234,"list":[{"code":111,"indent":0,"parameters":[1,234,0,0,1]},{"code":205,"indent":1,"parameters":[-1,{"list":[{"code":45,"parameters":["this.act($gameVariables.value(234))"],"indent":null},{"code":0}],"repeat":false,"skippable":false,"wait":false}]},{"code":505,"indent":1,"parameters":[{"code":45,"parameters":["this.act($gameVariables.value(234))"],"indent":null}]},{"code":0,"indent":1,"parameters":[]},{"code":412,"indent":0,"parameters":[]},{"code":0,"indent":0,"parameters":[]}],"name":"技能D","switchId":26,"trigger":0},
{"id":235,"list":[{"code":121,"indent":0,"parameters":[236,236,0]},{"code":231,"indent":0,"parameters":[1,"bnzs",0,0,298,100,100,100,255,0]},{"code":355,"indent":0,"parameters":["this.pluginCommand(\"MapSelectSkill\",[\"237\",\"1\",\"1\"])"]},{"code":235,"indent":0,"parameters":[1]},{"code":0,"indent":0,"parameters":[]}],"name":"---------技能F选择界面","switchId":1,"trigger":0},
{"id":236,"list":[{"code":111,"indent":0,"parameters":[1,237,0,0,1]},{"code":355,"indent":1,"parameters":["Galv.SBTNS.addButton(12,'map',1 * 0 + $gameVariables.value(237) ,705,688,['event',235],255);"]},{"code":121,"indent":1,"parameters":[236,236,1]},{"code":0,"indent":1,"parameters":[]},{"code":412,"indent":0,"parameters":[]},{"code":0,"indent":0,"parameters":[]}],"name":"技能F更换","switchId":236,"trigger":1},
{"id":237,"list":[{"code":111,"indent":0,"parameters":[1,237,0,0,1]},{"code":205,"indent":1,"parameters":[-1,{"list":[{"code":45,"parameters":["this.act($gameVariables.value(237))"],"indent":null},{"code":0}],"repeat":false,"skippable":false,"wait":false}]},{"code":505,"indent":1,"parameters":[{"code":45,"parameters":["this.act($gameVariables.value(237))"],"indent":null}]},{"code":0,"indent":1,"parameters":[]},{"code":412,"indent":0,"parameters":[]},{"code":0,"indent":0,"parameters":[]}],"name":"技能F","switchId":26,"trigger":0},
{"id":238,"list":[{"code":0,"indent":0,"parameters":[]}],"name":"","switchId":1,"trigger":0},
{"id":239,"list":[{"code":0,"indent":0,"parameters":[]}],"name":"","switchId":1,"trigger":0},
{"id":240,"list":[{"code":0,"indent":0,"parameters":[]}],"name":"攻击","switchId":1,"trigger":0},
{"id":241,"list":[{"code":111,"indent":0,"parameters":[12,"$gamePlayer.isJumpingV()"]},{"code":111,"indent":1,"parameters":[11,"left"]},{"code":355,"indent":2,"parameters":["$gamePlayer.jumpD(-1,10)"]},{"code":0,"indent":2,"parameters":[]},{"code":411,"indent":1,"parameters":[]},{"code":111,"indent":2,"parameters":[11,"right"]},{"code":355,"indent":3,"parameters":["$gamePlayer.jumpD(1,10)"]},{"code":0,"indent":3,"parameters":[]},{"code":412,"indent":2,"parameters":[]},{"code":0,"indent":2,"parameters":[]},{"code":412,"indent":1,"parameters":[]},{"code":0,"indent":1,"parameters":[]},{"code":412,"indent":0,"parameters":[]},{"code":0,"indent":0,"parameters":[]}],"name":"跳","switchId":10,"trigger":2},
{"id":242,"list":[{"code":0,"indent":0,"parameters":[]}],"name":"","switchId":1,"trigger":0},
{"id":243,"list":[{"code":111,"indent":0,"parameters":[0,21,0]},{"code":111,"indent":1,"parameters":[4,1,6,3]},{"code":121,"indent":2,"parameters":[10,10,0]},{"code":111,"indent":2,"parameters":[12,"$gamePlayer.jumpNum() <2"]},{"code":111,"indent":3,"parameters":[11,"left"]},{"code":108,"indent":4,"parameters":["左跳"]},{"code":250,"indent":4,"parameters":[{"name":"Jump","volume":90,"pitch":100,"pan":0}]},{"code":355,"indent":4,"parameters":["$gamePlayer.jumpV(-3,2,15) "]},{"code":111,"indent":4,"parameters":[12,"$gamePlayer.jumpNum() == 2"]},{"code":121,"indent":5,"parameters":[10,10,1]},{"code":212,"indent":5,"parameters":[-1,2,false]},{"code":108,"indent":5,"parameters":["飞第一次"]},{"code":250,"indent":5,"parameters":[{"name":"Jump","volume":90,"pitch":100,"pan":0}]},{"code":355,"indent":5,"parameters":["$gamePlayer.jumpV(-6,1,15) "]},{"code":0,"indent":5,"parameters":[]},{"code":412,"indent":4,"parameters":[]},{"code":0,"indent":4,"parameters":[]},{"code":411,"indent":3,"parameters":[]},{"code":111,"indent":4,"parameters":[11,"right"]},{"code":250,"indent":5,"parameters":[{"name":"Jump","volume":90,"pitch":100,"pan":0}]},{"code":108,"indent":5,"parameters":["右跳"]},{"code":355,"indent":5,"parameters":["$gamePlayer.jumpV(3,2,15) "]},{"code":111,"indent":5,"parameters":[12,"$gamePlayer.jumpNum() == 2"]},{"code":121,"indent":6,"parameters":[10,10,1]},{"code":212,"indent":6,"parameters":[-1,3,false]},{"code":108,"indent":6,"parameters":["飞第一次"]},{"code":250,"indent":6,"parameters":[{"name":"Jump","volume":90,"pitch":100,"pan":0}]},{"code":355,"indent":6,"parameters":["$gamePlayer.jumpV(6,1,15) "]},{"code":0,"indent":6,"parameters":[]},{"code":412,"indent":5,"parameters":[]},{"code":0,"indent":5,"parameters":[]},{"code":411,"indent":4,"parameters":[]},{"code":111,"indent":5,"parameters":[11,"down"]},{"code":250,"indent":6,"parameters":[{"name":"Jump","volume":90,"pitch":100,"pan":0}]},{"code":108,"indent":6,"parameters":["下跳"]},{"code":355,"indent":6,"parameters":["$gamePlayer.jumpV(0,-4,15) "]},{"code":0,"indent":6,"parameters":[]},{"code":411,"indent":5,"parameters":[]},{"code":108,"indent":6,"parameters":["原地"]},{"code":250,"indent":6,"parameters":[{"name":"Jump","volume":90,"pitch":100,"pan":0}]},{"code":355,"indent":6,"parameters":["$gamePlayer.jumpV(0,2,20) "]},{"code":0,"indent":6,"parameters":[]},{"code":412,"indent":5,"parameters":[]},{"code":0,"indent":5,"parameters":[]},{"code":412,"indent":4,"parameters":[]},{"code":0,"indent":4,"parameters":[]},{"code":412,"indent":3,"parameters":[]},{"code":0,"indent":3,"parameters":[]},{"code":412,"indent":2,"parameters":[]},{"code":0,"indent":2,"parameters":[]},{"code":411,"indent":1,"parameters":[]},{"code":121,"indent":2,"parameters":[10,10,0]},{"code":108,"indent":2,"parameters":["---------------------------------------------------------------------"]},{"code":111,"indent":2,"parameters":[12,"$gamePlayer.jumpNum() <1"]},{"code":111,"indent":3,"parameters":[11,"left"]},{"code":108,"indent":4,"parameters":["左跳"]},{"code":250,"indent":4,"parameters":[{"name":"Jump","volume":90,"pitch":100,"pan":0}]},{"code":355,"indent":4,"parameters":["$gamePlayer.jumpV(-3,2,20) "]},{"code":121,"indent":4,"parameters":[10,10,1]},{"code":0,"indent":4,"parameters":[]},{"code":411,"indent":3,"parameters":[]},{"code":111,"indent":4,"parameters":[11,"right"]},{"code":250,"indent":5,"parameters":[{"name":"Jump","volume":90,"pitch":100,"pan":0}]},{"code":108,"indent":5,"parameters":["右跳"]},{"code":355,"indent":5,"parameters":["$gamePlayer.jumpV(3,2,20) "]},{"code":121,"indent":5,"parameters":[10,10,1]},{"code":0,"indent":5,"parameters":[]},{"code":411,"indent":4,"parameters":[]},{"code":111,"indent":5,"parameters":[11,"down"]},{"code":250,"indent":6,"parameters":[{"name":"Jump","volume":90,"pitch":100,"pan":0}]},{"code":108,"indent":6,"parameters":["下跳"]},{"code":355,"indent":6,"parameters":["$gamePlayer.jumpV(0,-2,20) "]},{"code":121,"indent":6,"parameters":[10,10,1]},{"code":0,"indent":6,"parameters":[]},{"code":411,"indent":5,"parameters":[]},{"code":250,"indent":6,"parameters":[{"name":"Jump","volume":90,"pitch":100,"pan":0}]},{"code":355,"indent":6,"parameters":["$gamePlayer.jumpV(0,2,20) "]},{"code":108,"indent":6,"parameters":["原地"]},{"code":121,"indent":6,"parameters":[10,10,1]},{"code":0,"indent":6,"parameters":[]},{"code":412,"indent":5,"parameters":[]},{"code":0,"indent":5,"parameters":[]},{"code":412,"indent":4,"parameters":[]},{"code":0,"indent":4,"parameters":[]},{"code":412,"indent":3,"parameters":[]},{"code":0,"indent":3,"parameters":[]},{"code":412,"indent":2,"parameters":[]},{"code":0,"indent":2,"parameters":[]},{"code":412,"indent":1,"parameters":[]},{"code":0,"indent":1,"parameters":[]},{"code":412,"indent":0,"parameters":[]},{"code":0,"indent":0,"parameters":[]}],"name":"跳跃","switchId":10,"trigger":0},
{"id":244,"list":[{"code":121,"indent":0,"parameters":[245,245,0]},{"code":231,"indent":0,"parameters":[1,"bnzs",0,0,298,100,100,100,255,0]},{"code":355,"indent":0,"parameters":["this.pluginCommand(\"MapSelectSkill\",[\"246\",\"1\",\"1\"])"]},{"code":235,"indent":0,"parameters":[1]},{"code":0,"indent":0,"parameters":[]}],"name":"---------技能C选择界面","switchId":1,"trigger":0},
{"id":245,"list":[{"code":111,"indent":0,"parameters":[1,246,0,0,1]},{"code":355,"indent":1,"parameters":["Galv.SBTNS.addButton(15,'map',1 * 0 + 9 ,670,723,['event',300],255);"]},{"code":121,"indent":1,"parameters":[245,245,1]},{"code":0,"indent":1,"parameters":[]},{"code":412,"indent":0,"parameters":[]},{"code":0,"indent":0,"parameters":[]}],"name":"技能C更换","switchId":245,"trigger":1},
{"id":246,"list":[{"code":111,"indent":0,"parameters":[1,246,0,0,1]},{"code":205,"indent":1,"parameters":[-1,{"list":[{"code":45,"parameters":["this.act(9)"],"indent":null},{"code":0}],"repeat":false,"skippable":false,"wait":false}]},{"code":505,"indent":1,"parameters":[{"code":45,"parameters":["this.act(9)"],"indent":null}]},{"code":0,"indent":1,"parameters":[]},{"code":412,"indent":0,"parameters":[]},{"code":0,"indent":0,"parameters":[]}],"name":"技能C","switchId":26,"trigger":0},
{"id":247,"list":[{"code":121,"indent":0,"parameters":[248,248,0]},{"code":231,"indent":0,"parameters":[1,"bnzs",0,0,298,100,100,100,255,0]},{"code":355,"indent":0,"parameters":["this.pluginCommand(\"MapSelectSkill\",[\"249\",\"1\",\"1\"])"]},{"code":235,"indent":0,"parameters":[1]},{"code":0,"indent":0,"parameters":[]}],"name":"---------技能V选择界面","switchId":1,"trigger":0},
{"id":248,"list":[{"code":111,"indent":0,"parameters":[1,249,0,0,1]},{"code":355,"indent":1,"parameters":["Galv.SBTNS.addButton(16,'map',1 * 0 + $gameVariables.value(249) ,705,723,['event',247],255);"]},{"code":121,"indent":1,"parameters":[248,248,1]},{"code":0,"indent":1,"parameters":[]},{"code":412,"indent":0,"parameters":[]},{"code":0,"indent":0,"parameters":[]}],"name":"技能V更换","switchId":248,"trigger":1},
{"id":249,"list":[{"code":111,"indent":0,"parameters":[1,249,0,0,1]},{"code":205,"indent":1,"parameters":[-1,{"list":[{"code":45,"parameters":["this.act($gameVariables.value(249))"],"indent":null},{"code":0}],"repeat":false,"skippable":false,"wait":false}]},{"code":505,"indent":1,"parameters":[{"code":45,"parameters":["this.act($gameVariables.value(249))"],"indent":null}]},{"code":0,"indent":1,"parameters":[]},{"code":412,"indent":0,"parameters":[]},{"code":0,"indent":0,"parameters":[]}],"name":"技能V","switchId":26,"trigger":0},
{"id":250,"list":[{"code":0,"indent":0,"parameters":[]}],"name":"----------------------","switchId":1,"trigger":0},
{"id":251,"list":[{"code":0,"indent":0,"parameters":[]}],"name":"u","switchId":1,"trigger":0},
{"id":252,"list":[{"code":0,"indent":0,"parameters":[]}],"name":"i","switchId":1,"trigger":0},
{"id":253,"list":[{"code":0,"indent":0,"parameters":[]}],"name":"j","switchId":1,"trigger":0},
{"id":254,"list":[{"code":0,"indent":0,"parameters":[]}],"name":"k","switchId":1,"trigger":0},
{"id":255,"list":[{"code":0,"indent":0,"parameters":[]}],"name":"","switchId":1,"trigger":0},
{"id":256,"list":[{"code":0,"indent":0,"parameters":[]}],"name":"","switchId":1,"trigger":0},
{"id":257,"list":[{"code":0,"indent":0,"parameters":[]}],"name":"","switchId":1,"trigger":0},
{"id":258,"list":[{"code":0,"indent":0,"parameters":[]}],"name":"","switchId":1,"trigger":0},
{"id":259,"list":[{"code":0,"indent":0,"parameters":[]}],"name":"","switchId":1,"trigger":0},
{"id":260,"list":[{"code":0,"indent":0,"parameters":[]}],"name":"","switchId":1,"trigger":0},
{"id":261,"list":[{"code":0,"indent":0,"parameters":[]}],"name":"","switchId":1,"trigger":0},
{"id":262,"list":[{"code":0,"indent":0,"parameters":[]}],"name":"","switchId":1,"trigger":0},
{"id":263,"list":[{"code":0,"indent":0,"parameters":[]}],"name":"","switchId":1,"trigger":0},
{"id":264,"list":[{"code":0,"indent":0,"parameters":[]}],"name":"","switchId":1,"trigger":0},
{"id":265,"list":[{"code":0,"indent":0,"parameters":[]}],"name":"","switchId":1,"trigger":0},
{"id":266,"list":[{"code":0,"indent":0,"parameters":[]}],"name":"","switchId":1,"trigger":0},
{"id":267,"list":[{"code":0,"indent":0,"parameters":[]}],"name":"","switchId":1,"trigger":0},
{"id":268,"list":[{"code":0,"indent":0,"parameters":[]}],"name":"","switchId":1,"trigger":0},
{"id":269,"list":[{"code":0,"indent":0,"parameters":[]}],"name":"","switchId":1,"trigger":0},
{"id":270,"list":[{"code":0,"indent":0,"parameters":[]}],"name":"","switchId":1,"trigger":0},
{"id":271,"list":[{"code":0,"indent":0,"parameters":[]}],"name":"","switchId":1,"trigger":0},
{"id":272,"list":[{"code":0,"indent":0,"parameters":[]}],"name":"","switchId":1,"trigger":0},
{"id":273,"list":[{"code":0,"indent":0,"parameters":[]}],"name":"","switchId":1,"trigger":0},
{"id":274,"list":[{"code":0,"indent":0,"parameters":[]}],"name":"","switchId":1,"trigger":0},
{"id":275,"list":[{"code":0,"indent":0,"parameters":[]}],"name":"","switchId":1,"trigger":0},
{"id":276,"list":[{"code":0,"indent":0,"parameters":[]}],"name":"","switchId":1,"trigger":0},
{"id":277,"list":[{"code":0,"indent":0,"parameters":[]}],"name":"","switchId":1,"trigger":0},
{"id":278,"list":[{"code":0,"indent":0,"parameters":[]}],"name":"","switchId":1,"trigger":0},
{"id":279,"list":[{"code":0,"indent":0,"parameters":[]}],"name":"","switchId":1,"trigger":0},
{"id":280,"list":[{"code":0,"indent":0,"parameters":[]}],"name":"","switchId":1,"trigger":0},
{"id":281,"list":[{"code":0,"indent":0,"parameters":[]}],"name":"","switchId":1,"trigger":0},
{"id":282,"list":[{"code":0,"indent":0,"parameters":[]}],"name":"","switchId":1,"trigger":0},
{"id":283,"list":[{"code":0,"indent":0,"parameters":[]}],"name":"","switchId":1,"trigger":0},
{"id":284,"list":[{"code":0,"indent":0,"parameters":[]}],"name":"","switchId":1,"trigger":0},
{"id":285,"list":[{"code":0,"indent":0,"parameters":[]}],"name":"","switchId":1,"trigger":0},
{"id":286,"list":[{"code":0,"indent":0,"parameters":[]}],"name":"","switchId":1,"trigger":0},
{"id":287,"list":[{"code":0,"indent":0,"parameters":[]}],"name":"","switchId":1,"trigger":0},
{"id":288,"list":[{"code":0,"indent":0,"parameters":[]}],"name":"","switchId":1,"trigger":0},
{"id":289,"list":[{"code":0,"indent":0,"parameters":[]}],"name":"","switchId":1,"trigger":0},
{"id":290,"list":[{"code":0,"indent":0,"parameters":[]}],"name":"","switchId":1,"trigger":0},
{"id":291,"list":[{"code":0,"indent":0,"parameters":[]}],"name":"","switchId":1,"trigger":0},
{"id":292,"list":[{"code":0,"indent":0,"parameters":[]}],"name":"","switchId":1,"trigger":0},
{"id":293,"list":[{"code":0,"indent":0,"parameters":[]}],"name":"","switchId":1,"trigger":0},
{"id":294,"list":[{"code":0,"indent":0,"parameters":[]}],"name":"","switchId":1,"trigger":0},
{"id":295,"list":[{"code":0,"indent":0,"parameters":[]}],"name":"","switchId":1,"trigger":0},
{"id":296,"list":[{"code":0,"indent":0,"parameters":[]}],"name":"","switchId":1,"trigger":0},
{"id":297,"list":[{"code":0,"indent":0,"parameters":[]}],"name":"","switchId":1,"trigger":0},
{"id":298,"list":[{"code":0,"indent":0,"parameters":[]}],"name":"","switchId":1,"trigger":0},
{"id":299,"list":[{"code":0,"indent":0,"parameters":[]}],"name":"","switchId":1,"trigger":0},
{"id":300,"list":[{"code":0,"indent":0,"parameters":[]}],"name":"","switchId":1,"trigger":0}
]